dnndraw/__init__.py
dnndraw/engine.py
dnndraw/graph.py
dnndraw-0.2.0.dist-info/LICENSE
dnndraw-0.2.0.dist-info/METADATA
dnndraw-0.2.0.dist-info/WHEEL
dnndraw-0.2.0.dist-info/top_level.txt
dnndraw-0.2.0.dist-info/RECORD
